passerine/__init__.py
passerine/common.py
passerine/exception.py
passerine/graph.py
passerine/data/__init__.py
passerine/data/base.py
passerine/data/compressor.py
passerine/data/exception.py
passerine/data/serializer.py
passerine/db/__init__.py
passerine/db/common.py
passerine/db/entity.py
passerine/db/exception.py
passerine/db/expression.py
passerine/db/fixture.py
passerine/db/manager.py
passerine/db/mapper.py
passerine/db/mochi.py
passerine/db/query.py
passerine/db/repository.py
passerine/db/session.py
passerine/db/uow.py
passerine/db/wrapper.py
passerine/db/driver/__init__.py
passerine/db/driver/interface.py
passerine/db/driver/mongodriver.py
passerine/db/driver/registrar.py
passerine/db/driver/riakdriver.py
passerine/db/metadata/__init__.py
passerine/db/metadata/entity.py
passerine/db/metadata/helper.py
passerine/decorator/__init__.py
passerine/decorator/common.py
passerine-1.3.0.dist-info/DESCRIPTION.rst
passerine-1.3.0.dist-info/METADATA
passerine-1.3.0.dist-info/RECORD
passerine-1.3.0.dist-info/WHEEL
passerine-1.3.0.dist-info/metadata.json
passerine-1.3.0.dist-info/top_level.txt
