Metadata-Version: 2.0
Name: passerine
Version: 1.3.0
Summary: A generic object relational mapper (ORM) and data abstraction layer (DAL) primarily designed for NoSQL databases.
Home-page: https://github.com/shiroyuki/passerine
Author: Juti Noppornpitak
Author-email: juti_n@yahoo.co.jp
License: MIT
Platform: UNKNOWN
Classifier: Development Status :: 5 - Production/Stable
Classifier: Intended Audience :: Developers
Classifier: License :: OSI Approved :: MIT License
Classifier: Operating System :: OS Independent
Classifier: Programming Language :: Python
Classifier: Programming Language :: Python :: 2.7
Classifier: Programming Language :: Python :: 3
Classifier: Topic :: Internet :: WWW/HTTP :: Dynamic Content
Classifier: Topic :: Software Development :: Libraries
Classifier: Topic :: Database
Requires-Dist: pymongo
